LICENSE
MANIFEST.in
README.md
quicktest.py
settings_test.py
setup.py
django_vkontakte_board.egg-info/PKG-INFO
django_vkontakte_board.egg-info/SOURCES.txt
django_vkontakte_board.egg-info/dependency_links.txt
django_vkontakte_board.egg-info/not-zip-safe
django_vkontakte_board.egg-info/requires.txt
django_vkontakte_board.egg-info/top_level.txt
vkontakte_board/__init__.py
vkontakte_board/__init__.pyc
vkontakte_board/admin.py
vkontakte_board/admin.pyc
vkontakte_board/factories.py
vkontakte_board/factories.pyc
vkontakte_board/models.py
vkontakte_board/models.pyc
vkontakte_board/tests.py
vkontakte_board/tests.pyc
vkontakte_board/migrations/0001_initial.py
vkontakte_board/migrations/0001_initial.pyc
vkontakte_board/migrations/0002_auto__del_field_comment_from_id__add_field_comment_author.py
vkontakte_board/migrations/0003_auto__chg_field_comment_remote_id__chg_field_topic_remote_id.py
vkontakte_board/migrations/0003_auto__chg_field_comment_remote_id__chg_field_topic_remote_id.pyc
vkontakte_board/migrations/0004_convert_remote_id_of_comments.py
vkontakte_board/migrations/0005_auto.py
vkontakte_board/migrations/0006_auto.py
vkontakte_board/migrations/__init__.py
vkontakte_board/migrations/__init__.pyc